cli/__init__.py
pepperbot-0.3.7.dist-info/METADATA
pepperbot-0.3.7.dist-info/WHEEL
pepperbot-0.3.7.dist-info/licenses/LICENSE
pepperbot/__init__.py
pepperbot/adapters/keaimao/__init__.py
pepperbot/adapters/keaimao/api/__init__.py
pepperbot/adapters/keaimao/event/__init__.py
pepperbot/adapters/onebot/__init__.py
pepperbot/adapters/onebot/api/__init__.py
pepperbot/adapters/onebot/event/__init__.py
pepperbot/adapters/onebot/models/__init__.py
pepperbot/adapters/onebot/models/group.py
pepperbot/adapters/onebot/models/message.py
pepperbot/adapters/onebot/models/user.py
pepperbot/adapters/telegram/__init__.py
pepperbot/adapters/telegram/api/__init__.py
pepperbot/adapters/telegram/event/__init__.py
pepperbot/adapters/universal/__init__.py
pepperbot/adapters/universal/api/__init__.py
pepperbot/adapters/universal/event/__init__.py
pepperbot/config.py
pepperbot/core/__init__.py
pepperbot/core/api/api_caller.py
pepperbot/core/api/decorators.py
pepperbot/core/event/__init__.py
pepperbot/core/event/base_adapter.py
pepperbot/core/event/handle.py
pepperbot/core/event/universal.py
pepperbot/core/event/utils.py
pepperbot/core/message/base.py
pepperbot/core/message/chain.py
pepperbot/core/message/segment.py
pepperbot/core/route/__init__.py
pepperbot/core/route/available/__init__.py
pepperbot/core/route/available/decorators.py
pepperbot/core/route/cache.py
pepperbot/core/route/hook.py
pepperbot/core/route/parse.py
pepperbot/core/route/utils.py
pepperbot/core/route/validate.py
pepperbot/exceptions.py
pepperbot/extensions/__init__.py
pepperbot/extensions/action/__init__.py
pepperbot/extensions/action/action.py
pepperbot/extensions/action/chain.py
pepperbot/extensions/action/decorators.py
pepperbot/extensions/action/runner.py
pepperbot/extensions/command/__init__.py
pepperbot/extensions/command/constant.py
pepperbot/extensions/command/handle.py
pepperbot/extensions/command/node.py
pepperbot/extensions/command/parser.py
pepperbot/extensions/command/pattern.py
pepperbot/extensions/command/sender.py
pepperbot/extensions/command/timeout.py
pepperbot/extensions/command/utils.py
pepperbot-0.3.7.dist-info/RECORD
