Metadata-Version: 2.1
Name: pepperbot
Version: 0.3.7
Summary: An intuitive multi-platform bot framework, easily forward messages among platforms, support QQ, WeChat, Telegram. 一个符合直觉的跨社交平台机器人框架，轻松地在平台间传递消息，支持QQ、微信、Telegram
Keywords: Telegram async asyncio bot chinese cqhttp cross-platform framework keaimao onebot pydantic pyrogram python qq type-annotations type-hint wechat
Home-page: https://github.com/SSmJaE/PepperBot
Author-Email: SSmJaE <ssmjae327@gmail.com>
License: MIT
Classifier: Programming Language :: Python
Project-URL: Documentation, https://SSmJaE.github.io/PepperBot
Project-URL: Homepage, https://github.com/SSmJaE/PepperBot
Project-URL: Repository, https://github.com/SSmJaE/PepperBot
Requires-Python: >=3.8
Requires-Dist: Pyrogram>=2.0.102
Requires-Dist: TgCrypto>=1.2.5
Requires-Dist: apscheduler>=3
Requires-Dist: arrow>=1.2.3
Requires-Dist: better-exceptions>=0.3.3
Requires-Dist: devtools>=0.10.0
Requires-Dist: httpx>=0.23.3
Requires-Dist: loguru>=0.6.0
Requires-Dist: ormar[orjson,sqlite]>=0.12.1
Requires-Dist: pydantic>=1.10.4
Requires-Dist: python-dotenv>=1.0.0
Requires-Dist: rich>=13.3.2
Requires-Dist: sanic>=23
